lmishell
setup.cfg
setup.py
lmi/__init__.py
lmi/scripts/__init__.py
lmi/scripts/_metacommand/__init__.py
lmi/scripts/_metacommand/cmdutil.py
lmi/scripts/_metacommand/exit.py
lmi/scripts/_metacommand/help.py
lmi/scripts/_metacommand/interactive.py
lmi/scripts/_metacommand/manager.py
lmi/scripts/_metacommand/toplevel.py
lmi/scripts/_metacommand/util.py
lmi/scripts/common/__init__.py
lmi/scripts/common/configuration.py
lmi/scripts/common/errors.py
lmi/scripts/common/lmi_logging.py
lmi/scripts/common/session.py
lmi/scripts/common/util.py
lmi/scripts/common/command/__init__.py
lmi/scripts/common/command/base.py
lmi/scripts/common/command/checkresult.py
lmi/scripts/common/command/endpoint.py
lmi/scripts/common/command/helper.py
lmi/scripts/common/command/lister.py
lmi/scripts/common/command/meta.py
lmi/scripts/common/command/multiplexer.py
lmi/scripts/common/command/select.py
lmi/scripts/common/command/session.py
lmi/scripts/common/command/show.py
lmi/scripts/common/command/util.py
lmi/scripts/common/formatter/__init__.py
lmi/scripts/common/formatter/command.py
lmi/scripts/common/versioncheck/__init__.py
lmi/scripts/common/versioncheck/parser.py
lmi/shell/LMIBaseObject.py
lmi/shell/LMICIMXMLClient.py
lmi/shell/LMIClass.py
lmi/shell/LMICompleter.py
lmi/shell/LMIConnection.py
lmi/shell/LMIConsole.py
lmi/shell/LMIConstantValues.py
lmi/shell/LMIDecorators.py
lmi/shell/LMIExceptions.py
lmi/shell/LMIFormatter.py
lmi/shell/LMIHelper.py
lmi/shell/LMIIndicationListener.py
lmi/shell/LMIInstance.py
lmi/shell/LMIInstanceName.py
lmi/shell/LMIJob.py
lmi/shell/LMIMethod.py
lmi/shell/LMINamespace.py
lmi/shell/LMIObjectFactory.py
lmi/shell/LMIReturnValue.py
lmi/shell/LMIShellCache.py
lmi/shell/LMIShellClient.py
lmi/shell/LMIShellConfig.py
lmi/shell/LMIShellLogger.py
lmi/shell/LMIShellOptions.py
lmi/shell/LMIShellVersion.py
lmi/shell/LMISubscription.py
lmi/shell/LMIUtil.py
lmi/shell/LMIWSMANClient.py
lmi/shell/__init__.py
lmi/shell/compat/CIMIndicationListener.py
openlmi_tools.egg-info/PKG-INFO
openlmi_tools.egg-info/SOURCES.txt
openlmi_tools.egg-info/dependency_links.txt
openlmi_tools.egg-info/entry_points.txt
openlmi_tools.egg-info/namespace_packages.txt
openlmi_tools.egg-info/not-zip-safe
openlmi_tools.egg-info/requires.txt
openlmi_tools.egg-info/top_level.txt