Metadata-Version: 1.1
Name: openlmi-tools
Version: 0.10.4
Summary: OpenLMI (non)interactive shell and meta-command
Home-page: http://fedorahosted.org/openlmi/
Author: Peter Hatina, Michal Minar
Author-email: phatina@redhat.com, miminar@redhat.com
License: GPLv2+
Platform: UNKNOWN
Classifier: License :: OSI Approved :: GNU General Public License v2 or later (GPLv2+)
Classifier: Operating System :: POSIX :: Linux
Classifier: Topic :: System :: Systems Administration
Classifier: Programming Language :: Python
Classifier: Programming Language :: Python :: 2
Classifier: Programming Language :: Python :: 2.7
Classifier: Intended Audience :: Developers
Classifier: Environment :: Console
